tangram_explore/ExploreLayers.vue
tangram_explore/LayerList.vue
tangram_explore/__init__.py
tangram_explore/index.ts
tangram_explore/store.ts
tangram_explore-0.3.0.dist-info/METADATA
tangram_explore-0.3.0.dist-info/WHEEL
tangram_explore-0.3.0.dist-info/entry_points.txt
tangram_explore-0.3.0.dist-info/RECORD
